setup.py
messenger_server_nagorny.egg-info/PKG-INFO
messenger_server_nagorny.egg-info/SOURCES.txt
messenger_server_nagorny.egg-info/dependency_links.txt
messenger_server_nagorny.egg-info/requires.txt
messenger_server_nagorny.egg-info/top_level.txt
server/__init__.py
server/server.py
server/common/__init__.py
server/common/decorators.py
server/common/default_conf.py
server/common/metaclasses.py
server/common/utils.py
server/logs/__init__.py
server/logs/log_configs/__init__.py
server/logs/log_configs/client_log_config.py
server/logs/log_configs/server_log_config.py
server/server/__init__.py
server/server/config_window.py
server/server/main_window.py
server/server/reg_user_window.py
server/server/remove_user_window.py
server/server/server_core.py
server/server/server_db.py
server/server/statistic_window.py
server/tests/__init__.py
server/tests/unittests/__init__.py
server/tests/unittests/test_client.py
server/tests/unittests/test_server.py
server/tests/unittests/test_utils.py