Metadata-Version: 1.0
Name: messenger-server-nagorny
Version: 0.0.1
Summary: messenger_server
Home-page: UNKNOWN
Author: Max Nagorny
Author-email: m.a.nagorny@yandex.ru
License: UNKNOWN
Platform: UNKNOWN
